pastream.py
_py_pastream.abi3.so
pastream-0.2.0.post2.dist-info/top_level.txt
pastream-0.2.0.post2.dist-info/METADATA
pastream-0.2.0.post2.dist-info/WHEEL
pastream-0.2.0.post2.dist-info/entry_points.txt
pastream-0.2.0.post2.dist-info/RECORD
pastream-0.2.0.post2.dist-info/LICENSE
