Metadata-Version: 2.1
Name: pastream
Version: 0.2.0.post2
Summary: GIL-less Portaudio Streams for Python
Home-page: http://github.com/tgarc/pastream
Author: Thomas J. Garcia
Author-email: toemossgarcia@gmail.com
License: MIT
Platform: any
Classifier: License :: OSI Approved :: MIT License
Classifier: Operating System :: OS Independent
Classifier: Programming Language :: Python
Classifier: Programming Language :: Python :: 2
Classifier: Programming Language :: Python :: 3
Classifier: Topic :: Multimedia :: Sound/Audio
License-File: LICENSE
Requires-Dist: pa_ringbuffer>=0.1.2
Requires-Dist: cffi>=1.0.0
Requires-Dist: soundfile>=0.9.0
Requires-Dist: sounddevice>=0.3.9
Provides-Extra: numpy
Requires-Dist: numpy; extra == "numpy"
